{"frames":{"rock4":{"frame":{"x":1682,"y":1851,"w":126,"h":32},"rotated":false,"trimmed":false,"spriteSourceSize":{"x":0,"y":0,"w":126,"h":32},"sourceSize":{"w":126,"h":32}},"water":{"frame":{"x":0,"y":0,"w":1920,"h":1500},"rotated":false,"trimmed":false,"spriteSourceSize":{"x":0,"y":0,"w":1920,"h":1500},"sourceSize":{"w":1920,"h":1500}},"buttonDown":{"frame":{"x":1390,"y":1884,"w":88,"h":18},"rotated":false,"trimmed":false,"spriteSourceSize":{"x":0,"y":0,"w":88,"h":18},"sourceSize":{"w":88,"h":18}},"buttonUp":{"frame":{"x":1301,"y":1884,"w":88,"h":18},"rotated":false,"trimmed":false,"spriteSourceSize":{"x":0,"y":0,"w":88,"h":18},"sourceSize":{"w":88,"h":18}},"indicatorGreen":{"frame":{"x":318,"y":1691,"w":1300,"h":100},"rotated":false,"trimmed":false,"spriteSourceSize":{"x":0,"y":0,"w":1300,"h":100},"sourceSize":{"w":1300,"h":100}},"indicatorRed":{"frame":{"x":0,"y":1815,"w":1300,"h":100},"rotated":false,"trimmed":false,"spriteSourceSize":{"x":0,"y":0,"w":1300,"h":100},"sourceSize":{"w":1300,"h":100}},"playerFreed":{"frame":{"x":488,"y":1501,"w":169,"h":189},"rotated":false,"trimmed":false,"spriteSourceSize":{"x":0,"y":0,"w":169,"h":189},"sourceSize":{"w":169,"h":189}},"playerTrapped":{"frame":{"x":318,"y":1501,"w":169,"h":189},"rotated":false,"trimmed":false,"spriteSourceSize":{"x":0,"y":0,"w":169,"h":189},"sourceSize":{"w":169,"h":189}},"puzzleDoor":{"frame":{"x":1301,"y":1815,"w":155,"h":35},"rotated":false,"trimmed":false,"spriteSourceSize":{"x":0,"y":0,"w":155,"h":35},"sourceSize":{"w":155,"h":35}},"rock1":{"frame":{"x":1301,"y":1851,"w":126,"h":32},"rotated":false,"trimmed":false,"spriteSourceSize":{"x":0,"y":0,"w":126,"h":32},"sourceSize":{"w":126,"h":32}},"rock2":{"frame":{"x":1428,"y":1851,"w":126,"h":32},"rotated":false,"trimmed":false,"spriteSourceSize":{"x":0,"y":0,"w":126,"h":32},"sourceSize":{"w":126,"h":32}},"rock3":{"frame":{"x":1555,"y":1851,"w":126,"h":32},"rotated":false,"trimmed":false,"spriteSourceSize":{"x":0,"y":0,"w":126,"h":32},"sourceSize":{"w":126,"h":32}},"tentacleSign":{"frame":{"x":0,"y":1501,"w":317,"h":313},"rotated":false,"trimmed":false,"spriteSourceSize":{"x":0,"y":0,"w":317,"h":313},"sourceSize":{"w":317,"h":313}}},"meta":{"app":"https://www.leshylabs.com/apps/sstool/","version":"Leshy SpriteSheet Tool v0.8.4","image":"puzzles.png","size":{"w":1920,"h":1915},"scale":1}}